README.md
setup.cfg
setup.py
kalasearch/__init__.py
kalasearch/client.py
kalasearch/config.py
kalasearch/http_client.py
kalasearch/index.py
kalasearch/kalasearch.py
kalasearch.egg-info/PKG-INFO
kalasearch.egg-info/SOURCES.txt
kalasearch.egg-info/dependency_links.txt
kalasearch.egg-info/requires.txt
kalasearch.egg-info/top_level.txt