Metadata-Version: 2.1
Name: kalasearch
Version: 0.0.5
Summary: 卡拉搜索SDK-五分钟帮你打造站内、app内搜索引擎，适用于APP、小程序、电商、软件服务等领域
Home-page: https://kalasearch.cn
Author: Eddie Xie
Author-email: oeddyo@gmail.com
License: MIT
Download-URL: https://github.com/oeddyo/kalasearch-python-sdk/archive/0.0.5.tar.gz
Keywords: 搜索,后端,中台,search,full-text search,搜索引擎,站内搜索
Platform: UNKNOWN
Classifier: Programming Language :: Python :: 3
Classifier: Programming Language :: Python :: 3.5
Classifier: Programming Language :: Python :: 3.6
Classifier: Programming Language :: Python :: 3.7
Classifier: Programming Language :: Python :: 3.8
Classifier: License :: OSI Approved :: MIT License
Classifier: Operating System :: OS Independent
Requires-Python: >=3
